{
    "searchParameters": {
        "q": "Red Rice",
        "type": "images",
        "engine": "google",
        "num": 10
    },
    "images": [
        {
            "title": "Mexican Red Rice",
            "imageUrl": "https://www.recipetineats.com/tachyon/2017/10/Mexican-Red-Rice_-2.jpg",
            "imageWidth": 964,
            "imageHeight": 1350,
            "thumbnailUrl": "https://encrypted-tbn0.gstatic.com/images?q=tbn:ANd9GcS67X4D9dMKgZ-rtxH4_9fiEGHOck46C0GFeFgvsI37ZlQYye9A&s",
            "thumbnailWidth": 190,
            "thumbnailHeight": 266,
            "source": "RecipeTin Eats",
            "domain": "www.recipetineats.com",
            "link": "https://www.recipetineats.com/mexican-red-rice/",
            "googleUrl": "https://www.google.com/imgres?imgurl=https%3A%2F%2Fwww.recipetineats.com%2Ftachyon%2F2017%2F10%2FMexican-Red-Rice_-2.jpg&tbnid=ZlLNoRcadarIQM&imgrefurl=https%3A%2F%2Fwww.recipetineats.com%2Fmexican-red-rice%2F&docid=flcVtMIs-IZQSM&w=964&h=1350&ved=0ahUKEwjrwuXDwKSJAxVmMzQIHTaEFmUQvFcIAigA",
            "position": 1
        },
        {
            "title": "Israeli Red Rice",
            "imageUrl": "https://www.thetasteofkosher.com/wp-content/uploads/2018/10/Israeli_red_rice.jpg.webp",
            "imageWidth": 600,
            "imageHeight": 900,
            "thumbnailUrl": "https://encrypted-tbn0.gstatic.com/images?q=tbn:ANd9GcREy3HinR84dsyCn5rPu0PghfjHJYwSDbfZ5l0kVgaCm1lrFdI&s",
            "thumbnailWidth": 183,
            "thumbnailHeight": 275,
            "source": "The Taste of Kosher",
            "domain": "www.thetasteofkosher.com",
            "link": "https://www.thetasteofkosher.com/israeli-red-rice/",
            "googleUrl": "https://www.google.com/imgres?imgurl=https%3A%2F%2Fwww.thetasteofkosher.com%2Fwp-content%2Fuploads%2F2018%2F10%2FIsraeli_red_rice.jpg.webp&tbnid=E3uI8WRmowZd6M&imgrefurl=https%3A%2F%2Fwww.thetasteofkosher.com%2Fisraeli-red-rice%2F&docid=mgTNh2jtiiu0RM&w=600&h=900&ved=0ahUKEwjrwuXDwKSJAxVmMzQIHTaEFmUQvFcIAygB",
            "position": 2
        },
        {
            "title": "Mexican Red Rice (Arroz Rojo)",
            "imageUrl": "https://zerowastechef.com/wp-content/uploads/2021/09/09.21-fluff-with-fork-before-serving-480x270.jpg?crop=1",
            "imageWidth": 480,
            "imageHeight": 270,
            "thumbnailUrl": "https://encrypted-tbn0.gstatic.com/images?q=tbn:ANd9GcS24h_j3qBgiFsomQCO5wlilJS2XNWqIg7kCUIQwYomYO1YCbs&s",
            "thumbnailWidth": 300,
            "thumbnailHeight": 168,
            "source": "Zero-Waste Chef",
            "domain": "zerowastechef.com",
            "link": "https://zerowastechef.com/2021/09/09/simple-restaurant-style-mexican-red-rice-arroz-rojo/",
            "googleUrl": "https://www.google.com/imgres?imgurl=https%3A%2F%2Fzerowastechef.com%2Fwp-content%2Fuploads%2F2021%2F09%2F09.21-fluff-with-fork-before-serving-480x270.jpg%3Fcrop%3D1&tbnid=DGlcrpWDaq-u6M&imgrefurl=https%3A%2F%2Fzerowastechef.com%2F2021%2F09%2F09%2Fsimple-restaurant-style-mexican-red-rice-arroz-rojo%2F&docid=nkJxbavoi67OaM&w=480&h=270&ved=0ahUKEwjrwuXDwKSJAxVmMzQIHTaEFmUQvFcIBCgC",
            "position": 3
        },
        {
            "title": "Chamoru Red Rice",
            "imageUrl": "https://flouredframe.com/wp-content/uploads/2020/12/chamoru-red-rice-ft-image-1200x1200-1-480x270.jpg",
            "imageWidth": 480,
            "imageHeight": 270,
            "thumbnailUrl": "https://encrypted-tbn0.gstatic.com/images?q=tbn:ANd9GcTvmwi2ZINmq3kjtX1moNUu83XW7vaJ4meTt2lkYi80-rB70udP&s",
            "thumbnailWidth": 300,
            "thumbnailHeight": 168,
            "source": "Floured Frame",
            "domain": "flouredframe.com",
            "link": "https://flouredframe.com/chamoru-red-rice/",
            "googleUrl": "https://www.google.com/imgres?imgurl=https%3A%2F%2Fflouredframe.com%2Fwp-content%2Fuploads%2F2020%2F12%2Fchamoru-red-rice-ft-image-1200x1200-1-480x270.jpg&tbnid=pBsoM9FJrezxjM&imgrefurl=https%3A%2F%2Fflouredframe.com%2Fchamoru-red-rice%2F&docid=rsueWL6X0O9f6M&w=480&h=270&ved=0ahUKEwjrwuXDwKSJAxVmMzQIHTaEFmUQvFcIBSgD",
            "position": 4
        },
        {
            "title": "Charleston Red Rice",
            "imageUrl": "https://blackpeoplesrecipes.com/wp-content/uploads/2023/09/IMG_2889-scaled.jpg",
            "imageWidth": 1707,
            "imageHeight": 2560,
            "thumbnailUrl": "https://encrypted-tbn0.gstatic.com/images?q=tbn:ANd9GcTyD5f_WeEe8WbyqMhMp4vEYTdoWEsQAuioghxwlxfWqxrMhzmo&s",
            "thumbnailWidth": 183,
            "thumbnailHeight": 275,
            "source": "Black People's Recipes",
            "domain": "blackpeoplesrecipes.com",
            "link": "https://blackpeoplesrecipes.com/charleston-red-rice/",
            "googleUrl": "https://www.google.com/imgres?imgurl=https%3A%2F%2Fblackpeoplesrecipes.com%2Fwp-content%2Fuploads%2F2023%2F09%2FIMG_2889-scaled.jpg&tbnid=Xj0hHbYdWgSSOM&imgrefurl=https%3A%2F%2Fblackpeoplesrecipes.com%2Fcharleston-red-rice%2F&docid=hjJIaJm00eaHCM&w=1707&h=2560&ved=0ahUKEwjrwuXDwKSJAxVmMzQIHTaEFmUQvFcIBigE",
            "position": 5
        },
        {
            "title": "Instant Pot Kerala Rice | How to cook Red Rice",
            "imageUrl": "https://gingerskillet.com/wp-content/uploads/2020/12/ipkeralarice_F-1.jpg",
            "imageWidth": 1000,
            "imageHeight": 1000,
            "thumbnailUrl": "https://encrypted-tbn0.gstatic.com/images?q=tbn:ANd9GcRPMxvdKwVw6O1M8NDh0upBvR4mEmhNOGJtoo0r86Ly81TAgsU&s",
            "thumbnailWidth": 225,
            "thumbnailHeight": 225,
            "source": "Ginger Skillet",
            "domain": "gingerskillet.com",
            "link": "https://gingerskillet.com/instant-pot-kerala-rice/",
            "googleUrl": "https://www.google.com/imgres?imgurl=https%3A%2F%2Fgingerskillet.com%2Fwp-content%2Fuploads%2F2020%2F12%2Fipkeralarice_F-1.jpg&tbnid=hEyGMMbRxQgApM&imgrefurl=https%3A%2F%2Fgingerskillet.com%2Finstant-pot-kerala-rice%2F&docid=sD_zlVFDq1m4sM&w=1000&h=1000&ved=0ahUKEwjrwuXDwKSJAxVmMzQIHTaEFmUQvFcIBygF",
            "position": 6
        },
        {
            "title": "What is Red Rice and Why it is a Famous Food of Bhutan",
            "imageUrl": "https://www.compassandfork.com/wp-content/uploads/2017/04/What-is-Red-Rice-and-Why-it-is-a-Famous-Food-of-Bhutan-Serving-2.jpg",
            "imageWidth": 682,
            "imageHeight": 1024,
            "thumbnailUrl": "https://encrypted-tbn0.gstatic.com/images?q=tbn:ANd9GcSMNXf87Rw_78NcwjZkHgBQV89hAela3iAkQHWGcUNP1WR4hl4&s",
            "thumbnailWidth": 183,
            "thumbnailHeight": 275,
            "source": "Compass & Fork",
            "domain": "compassandfork.com",
            "link": "https://compassandfork.com/recipe/what-is-red-rice-why-famous-food-bhutan/",
            "googleUrl": "https://www.google.com/imgres?imgurl=https%3A%2F%2Fwww.compassandfork.com%2Fwp-content%2Fuploads%2F2017%2F04%2FWhat-is-Red-Rice-and-Why-it-is-a-Famous-Food-of-Bhutan-Serving-2.jpg&tbnid=PGO3Ixix7Wl_mM&imgrefurl=https%3A%2F%2Fcompassandfork.com%2Frecipe%2Fwhat-is-red-rice-why-famous-food-bhutan%2F&docid=ZGhi7v_wvEREMM&w=682&h=1024&ved=0ahUKEwjrwuXDwKSJAxVmMzQIHTaEFmUQvFcICCgG",
            "position": 7
        },
        {
            "title": "Charleston Red Rice",
            "imageUrl": "https://www.allrecipes.com/thmb/6Tt7GrWcbRlJUa2NKTIPnG11loE=/1500x0/filters:no_upscale():max_bytes(150000):strip_icc()/214070charleston-red-riceCookingwithShelia4x3-61419501b2cd4868af473d79a17cf265.jpg",
            "imageWidth": 1500,
            "imageHeight": 1125,
            "thumbnailUrl": "https://encrypted-tbn0.gstatic.com/images?q=tbn:ANd9GcTSVXdr2Y7r_BKUMpnnqhqsmPVS8LFNqDn14aQDDmXKOZ7amvne&s",
            "thumbnailWidth": 259,
            "thumbnailHeight": 194,
            "source": "Allrecipes",
            "domain": "www.allrecipes.com",
            "link": "https://www.allrecipes.com/recipe/214070/charleston-red-rice/",
            "googleUrl": "https://www.google.com/imgres?imgurl=https%3A%2F%2Fwww.allrecipes.com%2Fthmb%2F6Tt7GrWcbRlJUa2NKTIPnG11loE%3D%2F1500x0%2Ffilters%3Ano_upscale()%3Amax_bytes(150000)%3Astrip_icc()%2F214070charleston-red-riceCookingwithShelia4x3-61419501b2cd4868af473d79a17cf265.jpg&tbnid=EYcjXFredmIfZM&imgrefurl=https%3A%2F%2Fwww.allrecipes.com%2Frecipe%2F214070%2Fcharleston-red-rice%2F&docid=xKnptqE21oFbqM&w=1500&h=1125&ved=0ahUKEwjrwuXDwKSJAxVmMzQIHTaEFmUQvFcICSgH",
            "position": 8
        },
        {
            "title": "How To Cook Whole Grain Thai Red Rice (Cargo Rice)",
            "imageUrl": "https://whattocooktoday.com/wp-content/uploads/2021/02/red-rice-8.jpg",
            "imageWidth": 1000,
            "imageHeight": 1500,
            "thumbnailUrl": "https://encrypted-tbn0.gstatic.com/images?q=tbn:ANd9GcRU-cK1YIHWLr495IRPo0J8P_DzQY6UWusp2ZQs7GUrWiXC4Fnv&s",
            "thumbnailWidth": 183,
            "thumbnailHeight": 275,
            "source": "What To Cook Today",
            "domain": "whattocooktoday.com",
            "link": "https://whattocooktoday.com/how-to-cook-red-rice.html",
            "googleUrl": "https://www.google.com/imgres?imgurl=https%3A%2F%2Fwhattocooktoday.com%2Fwp-content%2Fuploads%2F2021%2F02%2Fred-rice-8.jpg&tbnid=8x9pxTPC625DdM&imgrefurl=https%3A%2F%2Fwhattocooktoday.com%2Fhow-to-cook-red-rice.html&docid=hpg3E1f4eyWcVM&w=1000&h=1500&ved=0ahUKEwjrwuXDwKSJAxVmMzQIHTaEFmUQvFcICigI",
            "position": 9
        },
        {
            "title": "No, You Can't Have My Red Rice Recipe",
            "imageUrl": "https://www.foodandwine.com/thmb/SBM14MHZ_2glDQaIotm5tBWh8w0=/1500x0/filters:no_upscale():max_bytes(150000):strip_icc()/chanels-gullah-kitchen-red-rice-FT-BLOG0521-4-1b8507732e6e4b1e9f6a91535dad390c.jpg",
            "imageWidth": 1500,
            "imageHeight": 1005,
            "thumbnailUrl": "https://encrypted-tbn0.gstatic.com/images?q=tbn:ANd9GcSIsbme-hu2ZgpErtFZM6rrV8JPA5jiHvP7_STD6EwOXQVtr1P1&s",
            "thumbnailWidth": 274,
            "thumbnailHeight": 184,
            "source": "Food & Wine",
            "domain": "www.foodandwine.com",
            "link": "https://www.foodandwine.com/grains/rice/no-you-cant-have-my-red-rice-recipe",
            "googleUrl": "https://www.google.com/imgres?imgurl=https%3A%2F%2Fwww.foodandwine.com%2Fthmb%2FSBM14MHZ_2glDQaIotm5tBWh8w0%3D%2F1500x0%2Ffilters%3Ano_upscale()%3Amax_bytes(150000)%3Astrip_icc()%2Fchanels-gullah-kitchen-red-rice-FT-BLOG0521-4-1b8507732e6e4b1e9f6a91535dad390c.jpg&tbnid=nhuHFV_zW4UceM&imgrefurl=https%3A%2F%2Fwww.foodandwine.com%2Fgrains%2Frice%2Fno-you-cant-have-my-red-rice-recipe&docid=YDwXtBWJgUPiQM&w=1500&h=1005&ved=0ahUKEwjrwuXDwKSJAxVmMzQIHTaEFmUQvFcICygJ",
            "position": 10
        }
    ],
    "credits": 1
}